pykasso/__init__.py
pykasso/_misc/SKS_SETTINGS.yaml
pykasso/_misc/statistics.xlsx
pykasso/_misc/statistics_old.xlsx
pykasso/_typing/__init__.py
pykasso/_typing/types.py
pykasso/_utils.py
pykasso/_version.py
pykasso/analysis/__init__.py
pykasso/analysis/analysis.py
pykasso/core/__init__.py
pykasso/core/_validations.py
pykasso/core/_wrappers.py
pykasso/core/domain.py
pykasso/core/fracturation.py
pykasso/core/geologic_features.py
pykasso/core/grid.py
pykasso/core/points.py
pykasso/core/sks.py
pykasso/visualization/__init__.py
pykasso/visualization/_pyplot.py
pykasso/visualization/_pyvista.py
pykasso/visualization/main.py
pykasso-0.1.3.dist-info/LICENSE
pykasso-0.1.3.dist-info/METADATA
pykasso-0.1.3.dist-info/WHEEL
pykasso-0.1.3.dist-info/RECORD
