Metadata-Version: 2.1
Name: pykasso
Version: 0.1.3
Summary: Python project intended to simulate stochastic karst network
Home-page: https://github.com/randlab/pyKasso
License: GPL-3.0
Keywords: hydrogeology,3-D modeling,stochasticity
Author: François Miville
Author-email: francois@miville.org
Maintainer: François Miville
Maintainer-email: francois@miville.org
Requires-Python: >=3.9,<4.0
Classifier: Development Status :: 3 - Alpha
Classifier: License :: OSI Approved :: GNU General Public License v3 (GPLv3)
Classifier: Natural Language :: English
Classifier: Operating System :: OS Independent
Classifier: Programming Language :: Python :: 3
Classifier: Programming Language :: Python :: 3.9
Classifier: Programming Language :: Python :: 3.10
Classifier: Programming Language :: Python :: 3.11
Classifier: Programming Language :: Python :: 3.9
Classifier: Topic :: Scientific/Engineering
Provides-Extra: analysis
Provides-Extra: visualization
Requires-Dist: agd (>=0.1.31,<0.2.0)
Requires-Dist: imageio (>=2.26.1,<3.0.0) ; extra == "visualization"
Requires-Dist: matplotlib (>=3.6.2,<4.0.0)
Requires-Dist: mplstereonet (>=0.6.2,<0.7.0) ; extra == "analysis"
Requires-Dist: mpmath (>=1.2.1,<2.0.0)
Requires-Dist: networkx (>=3.0,<4.0) ; extra == "analysis"
Requires-Dist: numpy (>=1.22.0,<2.0.0)
Requires-Dist: openpyxl (>=3.0.10,<4.0.0)
Requires-Dist: pandas (>=1.5.2,<2.0.0)
Requires-Dist: plotly (>=5.13.1,<6.0.0)
Requires-Dist: pyqt5 (>=5.15.9,<6.0.0)
Requires-Dist: pyvista (>=0.37.0,<0.38.0) ; extra == "visualization"
Requires-Dist: pyyaml (>=6.0,<7.0)
Requires-Dist: scipy (>=1.9.3,<2.0.0)
Requires-Dist: shapely (>=2.0.1,<3.0.0)
Project-URL: Repository, https://github.com/randlab/pyKasso
